{"basicInfoEnable":"1","detailsDataEnable":"1","correspondenceDataEnable":"1","mapEnable":"1","formEnable":"1","templateName":"992","businessCardTitle":"Dorota Olkowska","basicInfoDescription":"Witamy na naszej stronie internetowej i zapraszamy do zapoznania si\u0119 z udost\u0119pnionymi informacjami. \nW przypadku pyta\u0144 zach\u0119camy do kontaktu bezpo\u015bredniego lub pozostawienia wiadomo\u015bci e-mail. \n\nPozdrawiamy serdecznie!","basicInfoSectionTitle":"O nas","detailsDataAddressEnable":"1","detailsDataAddressStreet":"G\u00f3rna","detailsDataAddressLocalNumber":"14","detailsDataAddressZipCode":"18-400","detailsDataAddressCity":"\u0141om\u017ca","detailsDataPhoneEnable":"1","detailsDataPhoneValue":"+48.508962074","detailsDataEmailEnable":"1","detailsDataEmailValue":"olkowskadorota@gmail.com","detailsDataNipEnable":"0","detailsDataNipValue":"","detailsDataLinkEnable":"0","detailsDataLinkValue":"","detailsDataSectionTitle":"Dane firmowe","correspondenceDataAddressEnable":"1","correspondenceDataAddressStreet":"G\u00f3rna","correspondenceDataAddressLocalNumber":"14","correspondenceDataAddressZipCode":"18-400","correspondenceDataAddressCity":"\u0141om\u017ca","correspondenceDataPhoneEnable":"0","correspondenceDataPhoneValue":"","correspondenceDataSectionTitle":"Adres korespondencyjny","mapLat":"","mapLng":"","mapApiKeyEnable":"0","mapApiKey":"","mapSectionTitle":"Lokalizacja","clientEmail":"olkowskadorota@gmail.com","formSectionTitle":"Formularz kontaktowy","offerEnable":"1","offerContent":"<b>Najlepszy wyb\u00f3r to nazwa.pl<\/b><br\/><br\/><p>Gwarantem powodzenia w biznesie jest niezawodny, profesjonalny i ciesz\u0105cy si\u0119 zaufaniem Partner.<\/p><p><b>Nazwa.pl<\/b> to <b>nr 1<\/b> w zakresie rejestracji domen i us\u0142ug hostingowych w Polsce. Z naszych us\u0142ug skorzysta\u0142o ponad <b>1 000 000<\/b> Klient\u00f3w, rejestruj\u0105c ponad <b>4 000 000<\/b> domen i uruchamiaj\u0105c ponad <b>500 000<\/b> us\u0142ug hostingowych. To my wyznaczamy standardy bezpiecze\u0144stwa w polskim Internecie. ZA pomoc\u0105 certyfikat\u00f3w nazwaSSL DV zabezpieczylismy ponad <b>600 000<\/b> domen obs\u0142ugiwanych na serwerach DNS Anycast nazwa.pl w 15 krajach.<\/p><b>Poznaj ofert\u0119 nazwa.pl<\/b><ul><li><b>Bezpieczna Domena<\/b> - najwy\u017csze bezpiecze\u0144stwo i szybko\u015b\u0107 dzia\u0142ania Twojej witryny.<\/li><li><b>Cloud Hosting<\/b> - szybki i niezawodny serwer w chmurze.<\/li><li><b>Poczta<\/b> - profesjonalny adres w sieci chroniony przed spamem i wirusami.<\/li><li><b>Wizyt\u00f3wka Internetowa<\/b> - wizerunek stworzony w\u0142asnor\u0119cznie w mniej ni\u017c 1 minut\u0119!<\/li><li><b>WordPress Cloud<\/b> - szybka platforma hostingowa, tysi\u0105ce mo\u017cliwo\u015bci zastosowania. <\/li><li><b>VPS<\/b> - elastyczny i wydajny, niezawodne \u015brodowisko dla Twojej strony WWW.<\/li><li><b>Certyfikat SSL<\/b> - gwarancja bezpiecze\u0144stwa ochrony danych w Internecie.<\/li><li><b>DNS Anycast<\/b> - szybko\u015b\u0107 \u0142adowania stron, dzi\u0119ki serwerom zlokalizowanym na ca\u0142ym \u015bwiecie.<\/li><\/ul><p>Wiemy jak wa\u017cne jest fachowe wsparcie. Do Pa\u0144stwa dyspozycji <b>o ka\u017cdej porze dnia i nocy<\/b> pozostaj\u0105 Konsultanci nazwa.pl<\/p><p>Do\u0142\u0105cz do zadowolonych Klient\u00f3w najcz\u0119\u015bciej wybieranego rejestratora domen i dostawcy hostingowego w Polsce!<\/p>","offerSectionTitle":"Oferta","forceHttps":"0","rodoEnable":"0","rodoValue":"","clientName":"Dorota Olkowska","showRodoSection":"true"}